{"version": "1", "message": "ERROR: Hidden Testcases server unreachable.", "problem_id": "ads2_m13_a1_1", "user_id": "saitejasedate", "score": {"sample": {"0": {"execution_time": 0.41092395782470703, "passed": true}, "1": {"execution_time": 0.40377259254455566, "passed": true}, "2": {"execution_time": 0.6856086254119873, "passed": true}, "3": {"execution_time": 0.5526854991912842, "passed": true}, "4": {"execution_time": 0.5296974182128906, "passed": true}, "5": {"execution_time": 0.49271726608276367, "passed": true}, "6": {"execution_time": 0.6046562194824219, "passed": true}, "7": {"execution_time": 0.5316982269287109, "passed": true}}}, "check_style_score": "1/1"}