{"version": "1", "message": "ERROR: Hidden Testcases server unreachable.", "problem_id": "ads2_m14_a1_1", "user_id": "saitejasedate", "score": {"sample": {"0": {"execution_time": 0.7239267826080322, "passed": true}, "1": {"execution_time": 0.7391455173492432, "passed": true}, "2": {"execution_time": 0.6741476058959961, "passed": true}, "3": {"execution_time": 0.7012403011322021, "passed": true}, "4": {"execution_time": 0.706080436706543, "passed": true}, "5": {"execution_time": 0.674616813659668, "passed": true}}}, "check_style_score": "1/1"}